pytest_timeit.py
pytest_timeit-0.2.0.dist-info/DESCRIPTION.rst
pytest_timeit-0.2.0.dist-info/METADATA
pytest_timeit-0.2.0.dist-info/RECORD
pytest_timeit-0.2.0.dist-info/WHEEL
pytest_timeit-0.2.0.dist-info/entry_points.txt
pytest_timeit-0.2.0.dist-info/metadata.json
pytest_timeit-0.2.0.dist-info/top_level.txt
